Metadata-Version: 2.1
Name: pypdftk-snap-wrkarnd
Version: 0.4
Summary: Python wrapper for PDFTK with snap installation workaround
Home-page: http://github.com/revolunet/pypdftk
Author: Julien Bouquillon
Author-email: julien@revolunet.com
License: UNKNOWN
Platform: UNKNOWN
Classifier: Development Status :: 4 - Beta
Classifier: Environment :: Web Environment
Classifier: Intended Audience :: Developers
Classifier: License :: OSI Approved :: BSD License
Classifier: Operating System :: OS Independent
Classifier: Programming Language :: Python
Classifier: Topic :: Utilities
